spicerecord/__init__.py
spicerecord/__main__.py
spicerecord/cli.py
spicerecord/record.py
spicerecord/version.py
spicerecord/wrapper.py
spicerecord-0.2.1.dist-info/LICENSE
spicerecord-0.2.1.dist-info/METADATA
spicerecord-0.2.1.dist-info/WHEEL
spicerecord-0.2.1.dist-info/entry_points.txt
spicerecord-0.2.1.dist-info/top_level.txt
spicerecord-0.2.1.dist-info/RECORD
