Metadata-Version: 2.1
Name: spicerecord
Version: 0.2.1
Summary: Record SPICE session to MP4 video
Home-page: https://github.com/JonathonReinhart/spice-record
Author: Jonathon Reinhart
Author-email: jonathon.reinhart@gmail.com
License: GPL v2 with wrapper exception
Platform: UNKNOWN
Classifier: Development Status :: 3 - Alpha
Classifier: Environment :: Console
Classifier: Intended Audience :: Developers
Classifier: License :: OSI Approved :: MIT License
Classifier: Natural Language :: English
Classifier: Operating System :: POSIX :: Linux
Requires-Python: >=3.5
Requires-Dist: PyGObject
Requires-Dist: libvirt-python
